borgllm/__init__.py
borgllm/borgllm.py
borgllm/core.py
borgllm/langchain.py
borgllm/openai.py
borgstats/__init__.py
borgstats/list_models.py
borgllm-2.0.0.dist-info/METADATA
borgllm-2.0.0.dist-info/WHEEL
borgllm-2.0.0.dist-info/licenses/LICENSE
borgllm-2.0.0.dist-info/RECORD
