Metadata-Version: 2.4
Name: borgllm
Version: 2.0.0
Summary: Universal LLM client with API key rotation, rate limit management, and custom fallback strategies. Drop-in OpenAI SDK replacement with optional LangChain support.
Author-email: Omar Kamali <borgllm@omarkama.li>
License: MIT
License-File: LICENSE
Requires-Python: <4.0,>=3.9
Requires-Dist: furl>=2.1.3
Requires-Dist: hatch<2.0.0,>=1.14.1
Requires-Dist: openai>=1.0.0
Requires-Dist: pydantic!=1.*,>=2.0.0
Requires-Dist: python-dotenv>=1.0.0
Requires-Dist: pyyaml>=6.0
Requires-Dist: tiktoken>=0.9.0
Requires-Dist: toml>=0.10.2
Provides-Extra: langchain
Requires-Dist: langchain-core<0.4.0,>=0.3.68; extra == 'langchain'
Requires-Dist: langchain-openai~=0.3.0; extra == 'langchain'
Requires-Dist: langchain~=0.3.0; extra == 'langchain'
Requires-Dist: langsmith<0.5.0,>=0.4.5; extra == 'langchain'
Provides-Extra: test
Requires-Dist: furo>=2021.11.16; extra == 'test'
Requires-Dist: langchain-core<0.4.0,>=0.3.68; extra == 'test'
Requires-Dist: langchain-openai~=0.3.0; extra == 'test'
Requires-Dist: langchain~=0.3.0; extra == 'test'
Requires-Dist: langsmith<0.5.0,>=0.4.5; extra == 'test'
Requires-Dist: pytest-asyncio>=0.21.0; extra == 'test'
Requires-Dist: pytest-mock>=3.10.0; extra == 'test'
Requires-Dist: pytest-timeout>=2.1.0; extra == 'test'
Requires-Dist: pytest>=7.0.0; extra == 'test'
Requires-Dist: sphinx>=4.0.0; extra == 'test'
